setup.cfg
setup.py
cagezzz/__init__.py
cagezzz/cagezzz.txt
cagezzz.egg-info/PKG-INFO
cagezzz.egg-info/SOURCES.txt
cagezzz.egg-info/dependency_links.txt
cagezzz.egg-info/top_level.txt
cagezzz/../LICENSE
cagezzz/../README.md