Metadata-Version: 1.1
Name: cagezzz
Version: 0.0.1
Summary: A package for getting more Cage in your life
Home-page: https://github.com/rhydomako/cagezzz
Author: Richard Hydomako
Author-email: rhydomako@gmail.com
License: The MIT License (MIT)
